LICENSE.txt
README.rst
setup.cfg
setup.py
flet_restyle/__init__.py
flet_restyle.egg-info/PKG-INFO
flet_restyle.egg-info/SOURCES.txt
flet_restyle.egg-info/dependency_links.txt
flet_restyle.egg-info/requires.txt
flet_restyle.egg-info/top_level.txt