Metadata-Version: 2.1
Name: flet-restyle
Version: 1.0.0
Summary: Flet ReStyle.
Home-page: https://github.com/xzripper/flet_restyle
Download-URL: https://github.com/xzripper/flet_restyle/archive/refs/tags/v1.0.0.tar.gz
Author: Ivan Perzhinsky.
Author-email: name1not1found.com@gmail.com
License: MIT
Keywords: utility
Classifier: Development Status :: 5 - Production/Stable 
Classifier: Intended Audience :: Developers
Classifier: Topic :: Utilities
Classifier: License :: OSI Approved :: MIT License
Classifier: Programming Language :: Python :: 3
License-File: LICENSE.txt
Requires-Dist: BlurWindow
